elvia_vault/__init__.py
elvia_vault/vault_client.py
elvia_vault-0.5.2.dist-info/METADATA
elvia_vault-0.5.2.dist-info/WHEEL
elvia_vault-0.5.2.dist-info/top_level.txt
elvia_vault-0.5.2.dist-info/RECORD
