Metadata-Version: 2.1
Name: elvia-vault
Version: 0.5.2
Summary: elvia-vault Python package
Author: Elvia
Requires-Dist: cryptography>=36.0.0
Requires-Dist: hvac>=1.0.2
Requires-Dist: kubernetes>=24.2.0
Requires-Dist: pyjwt>=2.5.0
Provides-Extra: dev
Requires-Dist: jupyterlab; extra == "dev"
